excel_util/__init__.py
excel_util/mk_book.py
mk_util-0.0.1.dist-info/LICENSE
mk_util-0.0.1.dist-info/METADATA
mk_util-0.0.1.dist-info/WHEEL
mk_util-0.0.1.dist-info/top_level.txt
mk_util-0.0.1.dist-info/RECORD
