Metadata-Version: 2.1
Name: mk-util
Version: 0.0.1
Summary: insert excel book, base xlwt
Home-page: https://gitee.com/maxinxz/mk_util_python
Author: max
Author-email: ma_ke_min@163.com
License: UNKNOWN
Project-URL: Bug Tracker, https://gitee.com/maxinxz/mk_util_python/issues
Platform: UNKNOWN
Classifier: Programming Language :: Python :: 3
Classifier: License :: OSI Approved :: MIT License
Classifier: Operating System :: OS Independent
Requires-Python: >=3.5
License-File: LICENSE
